skrape/__init__.py
skrape/client.py
skrape/errors.py
skrape_py-1.0.3.dist-info/METADATA
skrape_py-1.0.3.dist-info/WHEEL
skrape_py-1.0.3.dist-info/RECORD
