Metadata-Version: 2.3
Name: skrape-py
Version: 1.0.3
Summary: A Python library for easily interacting with Skrape.ai API with type-safe schemas using Pydantic
Author: jenslys
Requires-Python: >=3.11,<4.0
Classifier: Programming Language :: Python :: 3
Classifier: Programming Language :: Python :: 3.11
Classifier: Programming Language :: Python :: 3.12
Classifier: Programming Language :: Python :: 3.13
Requires-Dist: httpx (>=0.25.2,<0.26.0)
Requires-Dist: pydantic (>=2.5.2,<3.0.0)
Requires-Dist: python-dotenv (>=1.0.0,<2.0.0)
